bcblib/__init__.py
bcblib/Disruptome/__init__.py
bcblib/Functionnectome/__init__.py
bcblib/Parcellotron3000/__init__.py
bcblib/TDI_Disco/__init__.py
bcblib/TDI_Disco/tdi_disco.py
bcblib/anacom2/__init__.py
bcblib/anacom2/anacom2.py
bcblib/anacom2/clusters.py
bcblib/gui/__init__.py
bcblib/notebooks/.gitattributes
bcblib/notebooks/blob_robot_playground.ipynb
bcblib/notebooks/extraction_tensorboard_info.ipynb
bcblib/notebooks/runs/Dec19_09-36-08_tolhsadum-HP-laptop/events.out.tfevents.1702974968.tolhsadum-HP-laptop.16287.0
bcblib/scripts/__init__.py
bcblib/scripts/bcbseg.py
bcblib/scripts/copy_images_from_subfolders.py
bcblib/scripts/effectsize_T2R.py
bcblib/scripts/emuse.py
bcblib/scripts/generate_synth_lesions.py
bcblib/scripts/ml_results.py
bcblib/scripts/parcitron.py
bcblib/scripts/pick_up_matched_synth_lesions.py
bcblib/scripts/tck2trk.py
bcblib/scripts/trk2tck.py
bcblib/tests/test_parcitron.py
bcblib/tools/PCA.py
bcblib/tools/__init__.py
bcblib/tools/arrays_utils.py
bcblib/tools/blob_robot.py
bcblib/tools/brain_extract.py
bcblib/tools/constants.py
bcblib/tools/datamined_kruskal.py
bcblib/tools/disconnectome.py
bcblib/tools/divide_KMeans.py
bcblib/tools/divide_mask.py
bcblib/tools/emuse_utils.py
bcblib/tools/entropy.py
bcblib/tools/funcon.py
bcblib/tools/general_utils.py
bcblib/tools/images_utils.py
bcblib/tools/mat_transform.py
bcblib/tools/misc.py
bcblib/tools/nifti_utils.py
bcblib/tools/nii_stats.py
bcblib/tools/randomise_helper.py
bcblib/tools/read_log_anacom.py
bcblib/tools/segment.py
bcblib/tools/split_clusters.py
bcblib/tools/spreadsheet_io_utils.py
bcblib/tools/tractotron.py
bcblib/tools/umap_utils.py
bcblib/tools/visualisation.py
bcblib/tools/__pycache__/PCA.cpython-36.pyc
bcblib/tools/__pycache__/__init__.cpython-36.pyc
bcblib/tools/__pycache__/brain_extract.cpython-36.pyc
bcblib/tools/__pycache__/constants.cpython-36.pyc
bcblib/tools/__pycache__/divide_mask.cpython-36.pyc
bcblib/tools/__pycache__/mat_transform.cpython-36.pyc
bcblib-0.4.0.dist-info/LICENSE.txt
bcblib-0.4.0.dist-info/METADATA
bcblib-0.4.0.dist-info/WHEEL
bcblib-0.4.0.dist-info/entry_points.txt
bcblib-0.4.0.dist-info/top_level.txt
bcblib-0.4.0.dist-info/zip-safe
bcblib-0.4.0.dist-info/RECORD
