Metadata-Version: 2.1
Name: bcblib
Version: 0.4.0
Author: Chris Foulon, Michel Thiebaut de Schotten
Author-email: hd.chrisfoulon@gmail.com
Project-URL: Source, https://github.com/chrisfoulon/BCBlib
Project-URL: Bug Reports, https://github.com/chrisfoulon/BCBlib/issues
Project-URL: BCBlab website, http://bcblab.com
Keywords: brain neuroimaging nifti cellular-automata bcbtoolkit bcblab parcellation null-models
License-File: LICENSE.txt
Requires-Dist: nibabel >=3
Requires-Dist: numpy
Requires-Dist: six
Requires-Dist: scipy
Requires-Dist: nilearn
Requires-Dist: scikit-learn
Requires-Dist: tqdm
Requires-Dist: pandas
Requires-Dist: openpyxl
Requires-Dist: umap-learn
Requires-Dist: joblib
Requires-Dist: statsmodels
Requires-Dist: mne
